emaileer.py
kancyemail.py
emaileer-0.0.4.dist-info/METADATA
emaileer-0.0.4.dist-info/WHEEL
emaileer-0.0.4.dist-info/entry_points.txt
emaileer-0.0.4.dist-info/top_level.txt
emaileer-0.0.4.dist-info/RECORD
